Workbook

Sheet Couverture
B2: AUDIT EXCEL SECTORIEL BTP-SSI
B3: IM2S PROTECTION INCENDIE — Édition 2026 v1
B5: Établi par : LENAXIS / SECURE — David MUSEUR
B6: Date d'établissement : 27 mai 2026
B8: CONTENU DU CLASSEUR
B9: 1. Couverture | D9: Cette feuille — présentation et mode d'emploi
B10: 2. Tableau de bord | D10: Synthèse, scores par catégorie, graphique radar, indicateurs
B11: 3. Référentiel | D11: Liste des 11 catégories et leurs 397 critères
B12: 4. Audit | D12: Cœur du document — 397 critères à évaluer (Oui/Non/NR), avec cotation, commentaire, action, échéance, responsable
B13: 5. Plan d'action | D13: Liste filtrée des actions à conduire issues de l'audit
B14: 6. KPI HSE | D14: Tableau des indicateurs de suivi annuel
B17: MODE D'EMPLOI
B18: 1. Renseigner chaque critère dans la feuille « Audit » : colonne Réponse (Oui / Non / Non renseigné / Sans objet).
B19: 2. Coter la Note (1 = bonne maîtrise → 4 = défaillance grave) — laisser vide si Sans objet.
B20: 3. Indiquer Maîtrise (Oui / Partielle / Non).
B21: 4. Saisir un commentaire libre (constat sur site, preuve, document associé).
B22: 5. Pour les non-conformités, formuler une Action corrective avec Échéance et Responsable.
B23: 6. La feuille « Tableau de bord » se met à jour automatiquement (scores, radar).
B24: 7. Le « Plan d'action » filtre automatiquement les non-conformités (Réponse = Non ou Note ≥ 3).
B27: CHARTE GRAPHIQUE IM2S — Rouge #A00D1A — Gris #5A5B5C

Sheet Tableau de bord
B2: TABLEAU DE BORD HSE — IM2S PROTECTION INCENDIE
B4: Catégorie | C4: Nb critères | D4: Évalués | E4: Conformes (Oui) | F4: Non conformes (Non) | G4: Score
B5: A. Hauteur & EPI antichute | C5: =COUNTIF(Audit!A:A,B5) | D5: =COUNTIFS(Audit!A:A,B5,Audit!F:F,"<>") | E5: =COUNTIFS(Audit!A:A,B5,Audit!F:F,"Oui") | F5: =COUNTIFS(Audit!A:A,B5,Audit!F:F,"Non") | G5: =IFERROR(ROUND(E5/(E5+F5)*100,0),0)
B6: B. Électricité & habilitations | C6: =COUNTIF(Audit!A:A,B6) | D6: =COUNTIFS(Audit!A:A,B6,Audit!F:F,"<>") | E6: =COUNTIFS(Audit!A:A,B6,Audit!F:F,"Oui") | F6: =COUNTIFS(Audit!A:A,B6,Audit!F:F,"Non") | G6: =IFERROR(ROUND(E6/(E6+F6)*100,0),0)
B7: C. Incendie & explosion | C7: =COUNTIF(Audit!A:A,B7) | D7: =COUNTIFS(Audit!A:A,B7,Audit!F:F,"<>") | E7: =COUNTIFS(Audit!A:A,B7,Audit!F:F,"Oui") | F7: =COUNTIFS(Audit!A:A,B7,Audit!F:F,"Non") | G7: =IFERROR(ROUND(E7/(E7+F7)*100,0),0)
B8: D. Manutention & TMS | C8: =COUNTIF(Audit!A:A,B8) | D8: =COUNTIFS(Audit!A:A,B8,Audit!F:F,"<>") | E8: =COUNTIFS(Audit!A:A,B8,Audit!F:F,"Oui") | F8: =COUNTIFS(Audit!A:A,B8,Audit!F:F,"Non") | G8: =IFERROR(ROUND(E8/(E8+F8)*100,0),0)
B9: E. Risque routier | C9: =COUNTIF(Audit!A:A,B9) | D9: =COUNTIFS(Audit!A:A,B9,Audit!F:F,"<>") | E9: =COUNTIFS(Audit!A:A,B9,Audit!F:F,"Oui") | F9: =COUNTIFS(Audit!A:A,B9,Audit!F:F,"Non") | G9: =IFERROR(ROUND(E9/(E9+F9)*100,0),0)
B10: F. Risque chimique & poussières | C10: =COUNTIF(Audit!A:A,B10) | D10: =COUNTIFS(Audit!A:A,B10,Audit!F:F,"<>") | E10: =COUNTIFS(Audit!A:A,B10,Audit!F:F,"Oui") | F10: =COUNTIFS(Audit!A:A,B10,Audit!F:F,"Non") | G10: =IFERROR(ROUND(E10/(E10+F10)*100,0),0)
B11: G. Amiante & plomb | C11: =COUNTIF(Audit!A:A,B11) | D11: =COUNTIFS(Audit!A:A,B11,Audit!F:F,"<>") | E11: =COUNTIFS(Audit!A:A,B11,Audit!F:F,"Oui") | F11: =COUNTIFS(Audit!A:A,B11,Audit!F:F,"Non") | G11: =IFERROR(ROUND(E11/(E11+F11)*100,0),0)
B12: H. Co-activité & plan de prévention | C12: =COUNTIF(Audit!A:A,B12) | D12: =COUNTIFS(Audit!A:A,B12,Audit!F:F,"<>") | E12: =COUNTIFS(Audit!A:A,B12,Audit!F:F,"Oui") | F12: =COUNTIFS(Audit!A:A,B12,Audit!F:F,"Non") | G12: =IFERROR(ROUND(E12/(E12+F12)*100,0),0)
B13: I. RPS, organisation, charge mentale | C13: =COUNTIF(Audit!A:A,B13) | D13: =COUNTIFS(Audit!A:A,B13,Audit!F:F,"<>") | E13: =COUNTIFS(Audit!A:A,B13,Audit!F:F,"Oui") | F13: =COUNTIFS(Audit!A:A,B13,Audit!F:F,"Non") | G13: =IFERROR(ROUND(E13/(E13+F13)*100,0),0)
B14: J. Bruit, vibrations, ambiances physiques | C14: =COUNTIF(Audit!A:A,B14) | D14: =COUNTIFS(Audit!A:A,B14,Audit!F:F,"<>") | E14: =COUNTIFS(Audit!A:A,B14,Audit!F:F,"Oui") | F14: =COUNTIFS(Audit!A:A,B14,Audit!F:F,"Non") | G14: =IFERROR(ROUND(E14/(E14+F14)*100,0),0)
B15: K. Organisation, formation, suivi | C15: =COUNTIF(Audit!A:A,B15) | D15: =COUNTIFS(Audit!A:A,B15,Audit!F:F,"<>") | E15: =COUNTIFS(Audit!A:A,B15,Audit!F:F,"Oui") | F15: =COUNTIFS(Audit!A:A,B15,Audit!F:F,"Non") | G15: =IFERROR(ROUND(E15/(E15+F15)*100,0),0)
B16: TOTAL / SCORE GLOBAL | C16: =SUM(C5:C15) | D16: =SUM(D5:D15) | E16: =SUM(E5:E15) | F16: =SUM(F5:F15) | G16: =IFERROR(ROUND(E16/(E16+F16)*100,0),0)
B19: INDICATEURS DE SYNTHÈSE
B20: Nb total de critères | C20: =C16
B21: Nb de critères évalués | C21: =D16
B22: Taux d'évaluation (%) | C22: =IFERROR(ROUND(D16/C16*100,0),0)
B23: Nb conformes | C23: =E16
B24: Nb non-conformes | C24: =F16
B25: Score global de conformité (%) | C25: =G16
B26: Actions critiques (Note = 4) | C26: =COUNTIF(Audit!G:G,4)
B27: Actions élevées (Note = 3) | C27: =COUNTIF(Audit!G:G,3)

Sheet Référentiel
A1: Catégorie | B1: Sous-catégorie | C1: Code | D1: Critère | E1: Référence réglementaire/technique
A2: A. Hauteur & EPI antichute | B2: Échafaudages | C2: A.01 | D2: Échafaudages utilisés conformes à la norme NF EN 12810/12811 | E2: NF EN 12810/12811
A3: A. Hauteur & EPI antichute | B3: Échafaudages | C3: A.02 | D3: Montage / démontage par personne formée (R.408 CARSAT) | E3: Reco. CARSAT R.408
A4: A. Hauteur & EPI antichute | B4: Échafaudages | C4: A.03 | D4: Examen avant mise en service consigné dans le registre | E4: Art. R.4323-69
A5: A. Hauteur & EPI antichute | B5: Échafaudages | C5: A.04 | D5: Examen journalier de l'état de conservation avant utilisation | E5: Art. R.4323-70
A6: A. Hauteur & EPI antichute | B6: Échafaudages | C6: A.05 | D6: Examen trimestriel de fonctionnement et conformité | E6: Art. R.4323-71
A7: A. Hauteur & EPI antichute | B7: Échafaudages | C7: A.06 | D7: Plinthes de pied (≥ 15 cm) sur tous les niveaux de travail | E7: Art. R.4323-59
A8: A. Hauteur & EPI antichute | B8: Échafaudages | C8: A.07 | D8: Garde-corps principal à 1 m + sous-lisse à 45 cm + plinthe | E8: Art. R.4323-59
A9: A. Hauteur & EPI antichute | B9: Échafaudages | C9: A.08 | D9: Plancher complet, jointif, antidérapant | E9: Art. R.4323-69
A10: A. Hauteur & EPI antichute | B10: Échafaudages | C10: A.09 | D10: Accès aux niveaux par échelle intérieure ou escalier | E10: Art. R.4323-69
A11: A. Hauteur & EPI antichute | B11: Échafaudages | C11: A.10 | D11: Stabilisation par ancrages calculés (vent, charge, hauteur) | E11: NF EN 12811
A12: A. Hauteur & EPI antichute | B12: Échafaudages | C12: A.11 | D12: Note de calcul disponible pour échafaudages > 24 m | E12: Art. R.4323-69
... A398: K. Organisation, formation, suivi | B398: Communication | C398: K.45 | D398: Plan de communication HSE (newsletter, réunions, affichages) | E398: Bonne pratique

Sheet Audit
A1: Catégorie | B1: Sous-catégorie | C1: Code | D1: Critère | E1: Référence | F1: Réponse | G1: Note (1-4) | H1: Maîtrise | I1: Commentaire / Constat | J1: Action corrective | K1: Échéance | L1: Responsable
A2: A. Hauteur & EPI antichute | B2: Échafaudages | C2: A.01 | D2: Échafaudages utilisés conformes à la norme NF EN 12810/12811 | E2: NF EN 12810/12811
A3: A. Hauteur & EPI antichute | B3: Échafaudages | C3: A.02 | D3: Montage / démontage par personne formée (R.408 CARSAT) | E3: Reco. CARSAT R.408
A4: A. Hauteur & EPI antichute | B4: Échafaudages | C4: A.03 | D4: Examen avant mise en service consigné dans le registre | E4: Art. R.4323-69
A5: A. Hauteur & EPI antichute | B5: Échafaudages | C5: A.04 | D5: Examen journalier de l'état de conservation avant utilisation | E5: Art. R.4323-70
A6: A. Hauteur & EPI antichute | B6: Échafaudages | C6: A.05 | D6: Examen trimestriel de fonctionnement et conformité | E6: Art. R.4323-71
A7: A. Hauteur & EPI antichute | B7: Échafaudages | C7: A.06 | D7: Plinthes de pied (≥ 15 cm) sur tous les niveaux de travail | E7: Art. R.4323-59
A8: A. Hauteur & EPI antichute | B8: Échafaudages | C8: A.07 | D8: Garde-corps principal à 1 m + sous-lisse à 45 cm + plinthe | E8: Art. R.4323-59
A9: A. Hauteur & EPI antichute | B9: Échafaudages | C9: A.08 | D9: Plancher complet, jointif, antidérapant | E9: Art. R.4323-69
A10: A. Hauteur & EPI antichute | B10: Échafaudages | C10: A.09 | D10: Accès aux niveaux par échelle intérieure ou escalier | E10: Art. R.4323-69
A11: A. Hauteur & EPI antichute | B11: Échafaudages | C11: A.10 | D11: Stabilisation par ancrages calculés (vent, charge, hauteur) | E11: NF EN 12811
A12: A. Hauteur & EPI antichute | B12: Échafaudages | C12: A.11 | D12: Note de calcul disponible pour échafaudages > 24 m | E12: Art. R.4323-69
A13: A. Hauteur & EPI antichute | B13: PEMP (nacelles) | C13: A.12 | D13: CACES R.486 cat. A et/ou B en cours de validité (5 ans) | E13: Reco. CACES R.486
... A398: K. Organisation, formation, suivi | B398: Communication | C398: K.45 | D398: Plan de communication HSE (newsletter, réunions, affichages) | E398: Bonne pratique

Sheet Plan d'action
B2: PLAN D'ACTION HSE
B4: Utilisation : ce plan d'action se construit automatiquement à partir des non-conformités identifiées dans la feuille « Audit ». Pour le générer manuellement, filtrer la feuille « Audit » sur Réponse = Non OU Note ≥ 3, et copier les actions dans le tableau ci-dessous, ou utiliser le filtre AutoFilter directement.
B8: Code critère | C8: Catégorie | D8: Action corrective | E8: Échéance | F8: Responsable | G8: État | H8: Date réalisation | I8: Coût estimé

Sheet KPI HSE
A2: INDICATEURS DE SUIVI HSE
A4: Indicateur | B4: Cible 2026 | C4: Périodicité | D4: Source | E4: Valeur 2024 | F4: Valeur 2025 | G4: Valeur 2026
A5: Taux d'habilitations électriques en cours de validité | B5: 100% | C5: Trimestrielle | D5: Tableau habilitations
A6: Nb de SST formés en cours de validité | B6: ≥ 2 / 14 ETP | C6: Annuelle | D6: Registre formations
A7: Nb de causeries sécurité réalisées | B7: ≥ 6 / an | C7: Trimestrielle | D7: CR causeries
A8: Nb d'exercices d'évacuation (siège) | B8: ≥ 2 / an | C8: Annuelle | D8: CR exercices
A9: Taux de salariés formés PRAP (gestes & postures) | B9: 100% UT2-3-4-5 | C9: Semestrielle | D9: Attestations PRAP
A10: Nb de permis de feu délivrés | B10: 100% points chauds | C10: Trimestrielle | D10: Registre chantiers
A11: Plans de prévention signés | B11: 100% > 400h ou TD | C11: Trimestrielle | D11: Registre PdP
A12: Cartes BTP valides | B12: 100% | C12: Trimestrielle | D12: Tableau RH
A13: Taux de fréquence AT (TF) | B13: < moyenne NAF 43.21A | C13: Annuelle | D13: CARSAT
A14: Taux de gravité AT (TG) | B14: < moyenne NAF 43.21A | C14: Annuelle | D14: CARSAT
A15: Nb de presque-accidents remontés (signal positif) | B15: ≥ 6 / an | C15: Mensuelle | D15: Registre HS
A16: Visites médicales à jour | B16: 100% | C16: Trimestrielle | D16: Service Santé Travail
... A19: Q18 / Q19 levés dans les 3 mois | B19: 100% | C19: Annuelle | D19: Rapports vérification
